buildbot_react_grid_view/VERSION
buildbot_react_grid_view/__init__.py
buildbot_react_grid_view/static/scripts.js
buildbot_react_grid_view-4.0.4.dist-info/METADATA
buildbot_react_grid_view-4.0.4.dist-info/WHEEL
buildbot_react_grid_view-4.0.4.dist-info/entry_points.txt
buildbot_react_grid_view-4.0.4.dist-info/top_level.txt
buildbot_react_grid_view-4.0.4.dist-info/RECORD
