Metadata-Version: 2.1
Name: buildbot-react-grid-view
Version: 4.0.4
Summary: Buildbot Grid View plugin (React)
Home-page: http://buildbot.net/
Author: Robin Jarry
Author-email: robin.jarry@6wind.com
Classifier: License :: OSI Approved :: GNU General Public License v2 (GPLv2)
